{
	"TestMap": {
		"scene_name": "TestMap",
		"friendly_name": "Test Map",
		"starting_money": 1500,
		"waves": [
			{
				"enemies": [
					{"base": "TestEnemy", "category": "TestTank", "delay": 1.5},
					{"base": "TestEnemy", "category": "TestTank", "delay": 1.5},
					{"base": "TestEnemy", "category": "TestTank", "delay": 1.5},
					{"base": "TestEnemy", "category": "TestTank", "delay": 1.5},
					{"base": "TestEnemy", "category": "TestTank", "delay": 1.5},
					{"base": "TestEnemy", "category": "TestTank", "delay": 1.5}
				],
				"cost": 300
			},
			{
				"enemies": [
					{"base": "Tank", "category": "EnergyTank", "delay": 1.5},
					{"base": "Tank", "category": "LongTank", "delay": 1.5},
					{"base": "Tank", "category": "EnergyTank", "delay": 1.5},
					{"base": "Tank", "category": "LongTank", "delay": 1.5},
					{"base": "Tank", "category": "EnergyTank", "delay": 1.5},
					{"base": "Tank", "category": "LongTank", "delay": 1.5}
				],
				"cost": 300
			},
			{
				"enemies": [
					{"base": "Tank", "category": "EnergyTank", "delay": 1.5},
					{"base": "Tank", "category": "LongTank", "delay": 1.5},
					{"base": "Tank", "category": "EnergyTank", "delay": 1.5},
					{"base": "Tank", "category": "LongTank", "delay": 1.5},
					{"base": "Tank", "category": "EnergyTank", "delay": 1.5},
					{"base": "Tank", "category": "LongTank", "delay": 1.5}
				],
				"cost": 300
			},
			{
				"enemies": [
					{"base": "Tank", "category": "EnergyTank", "delay": 1.5},
					{"base": "Tank", "category": "LongTank", "delay": 1.5},
					{"base": "Tank", "category": "EnergyTank", "delay": 1.5},
					{"base": "Tank", "category": "LongTank", "delay": 1.5},
					{"base": "Tank", "category": "EnergyTank", "delay": 1.5},
					{"base": "Tank", "category": "LongTank", "delay": 1.5}
				],
				"cost": 300
			}
		]
	}
}
